dagster/__init__.py
dagster/__main__.py
dagster/_annotations.py
dagster/_builtins.py
dagster/_module_alias_map.py
dagster/py.typed
dagster/version.py
dagster/_api/__init__.py
dagster/_api/get_server_id.py
dagster/_api/list_repositories.py
dagster/_api/notebook_data.py
dagster/_api/snapshot_execution_plan.py
dagster/_api/snapshot_job.py
dagster/_api/snapshot_partition.py
dagster/_api/snapshot_repository.py
dagster/_api/snapshot_schedule.py
dagster/_api/snapshot_sensor.py
dagster/_check/__init__.py
dagster/_cli/__init__.py
dagster/_cli/api.py
dagster/_cli/asset.py
dagster/_cli/code_server.py
dagster/_cli/config_scaffolder.py
dagster/_cli/debug.py
dagster/_cli/definitions.py
dagster/_cli/dev.py
dagster/_cli/instance.py
dagster/_cli/job.py
dagster/_cli/project.py
dagster/_cli/proxy_server_manager.py
dagster/_cli/run.py
dagster/_cli/schedule.py
dagster/_cli/sensor.py
dagster/_cli/utils.py
dagster/_cli/workspace/__init__.py
dagster/_cli/workspace/cli_target.py
dagster/_config/__init__.py
dagster/_config/config_schema.py
dagster/_config/config_type.py
dagster/_config/errors.py
dagster/_config/evaluate_value_result.py
dagster/_config/field.py
dagster/_config/field_utils.py
dagster/_config/post_process.py
dagster/_config/primitive_mapping.py
dagster/_config/snap.py
dagster/_config/source.py
dagster/_config/stack.py
dagster/_config/traversal_context.py
dagster/_config/type_printer.py
dagster/_config/validate.py
dagster/_config/pythonic_config/__init__.py
dagster/_config/pythonic_config/attach_other_object_to_context.py
dagster/_config/pythonic_config/config.py
dagster/_config/pythonic_config/conversion_utils.py
dagster/_config/pythonic_config/io_manager.py
dagster/_config/pythonic_config/resource.py
dagster/_config/pythonic_config/type_check_utils.py
dagster/_config/pythonic_config/typing_utils.py
dagster/_core/__init__.py
dagster/_core/assets.py
dagster/_core/captured_log_api.py
dagster/_core/code_pointer.py
dagster/_core/debug.py
dagster/_core/decorator_utils.py
dagster-1.12.13.dist-info/licenses/LICENSE
dagster-1.12.13.dist-info/METADATA
dagster-1.12.13.dist-info/WHEEL
dagster-1.12.13.dist-info/entry_points.txt
dagster-1.12.13.dist-info/top_level.txt
dagster-1.12.13.dist-info/RECORD
